olr/__init__.py
olr/olr_function.py
olr-1.3.6.data/data/Lib/site-packages/olr/crudeoildata.csv
olr-1.3.6.dist-info/LICENSE.txt
olr-1.3.6.dist-info/METADATA
olr-1.3.6.dist-info/WHEEL
olr-1.3.6.dist-info/top_level.txt
olr-1.3.6.dist-info/RECORD
