Metadata-Version: 2.1
Name: olr
Version: 1.3.6
Summary: olr: Optimal Linear Regression
Home-page: https://www.github.com/MatHatter
Author: Mathew Fok
Author-email: quiksilver67213@yahoo.com
Classifier: Programming Language :: Python :: 3
Classifier: License :: OSI Approved :: GNU General Public License v3 (GPLv3)
Classifier: Operating System :: OS Independent
License-File: LICENSE.txt
Requires-Dist: pandas (>=1.0.0)
Requires-Dist: numpy (>=1.18.0)
